neraug/__init__.py
neraug/augmentator.py
neraug/scheme.py
neraug-0.1.1.dist-info/LICENSE
neraug-0.1.1.dist-info/METADATA
neraug-0.1.1.dist-info/WHEEL
neraug-0.1.1.dist-info/top_level.txt
neraug-0.1.1.dist-info/RECORD
