Metadata-Version: 2.1
Name: neraug
Version: 0.1.1
Summary: Data augmentation tool for named entity recognition
Home-page: https://github.com/Hironsan/neraug
Author: Hironsan
Author-email: hiroki.nakayama.py@gmail.com
License: MIT
Platform: UNKNOWN
Classifier: License :: OSI Approved :: MIT License
Classifier: Programming Language :: Python
Classifier: Programming Language :: Python :: 3.6
Classifier: Programming Language :: Python :: 3.7
Classifier: Programming Language :: Python :: 3.8
Classifier: Programming Language :: Python :: Implementation :: CPython
Classifier: Programming Language :: Python :: Implementation :: PyPy
Requires-Dist: seqeval
